wiimatch/__init__.py
wiimatch/containers.py
wiimatch/lsq_optimizer.py
wiimatch/match.py
wiimatch/utils.py
wiimatch/tests/__init__.py
wiimatch/tests/test_match.py
wiimatch/tests/test_utils.py
wiimatch-0.3.2.dist-info/LICENSE.txt
wiimatch-0.3.2.dist-info/METADATA
wiimatch-0.3.2.dist-info/WHEEL
wiimatch-0.3.2.dist-info/top_level.txt
wiimatch-0.3.2.dist-info/RECORD
