Metadata-Version: 2.1
Name: wiimatch
Version: 0.3.2
Summary: A package for optimal "matching" N-dimentional image background
Home-page: https://github.com/spacetelescope/wiimatch
Author: Mihai Cara
Author-email: help@stsci.edu
License: BSD-3-Clause
Project-URL: Bug Reports, https://github.com/spacetelescope/wiimatch/issues/
Project-URL: Source, https://github.com/spacetelescope/wiimatch/
Project-URL: Help, https://hsthelp.stsci.edu/
Classifier: Intended Audience :: Science/Research
Classifier: License :: OSI Approved :: BSD License
Classifier: Operating System :: OS Independent
Classifier: Programming Language :: Python
Classifier: Topic :: Scientific/Engineering :: Astronomy
Classifier: Topic :: Software Development :: Libraries :: Python Modules
Classifier: Development Status :: 3 - Alpha
Requires-Python: >=3.7
License-File: LICENSE.txt
Requires-Dist: numpy
Requires-Dist: scipy
Provides-Extra: all
Requires-Dist: scipy ; extra == 'all'
Provides-Extra: docs
Requires-Dist: numpydoc ; extra == 'docs'
Requires-Dist: graphviz ; extra == 'docs'
Requires-Dist: sphinx ; extra == 'docs'
Requires-Dist: sphinx-rtd-theme ; extra == 'docs'
Requires-Dist: stsci-rtd-theme ; extra == 'docs'
Requires-Dist: sphinx-automodapi ; extra == 'docs'
Provides-Extra: test
Requires-Dist: pytest ; extra == 'test'
Requires-Dist: pytest-cov ; extra == 'test'
Requires-Dist: pytest-doctestplus ; extra == 'test'
